{
    "001": [
        "Tower",
        "Lantern",
        "Skyscraper"
    ],
    "002": [
        "Person",
        "Woman",
        "Watercraft",
        "Clothing",
        "Boat"
    ],
    "003": [
        "Person",
        "Woman",
        "Man",
        "Clothing"
    ],
    "004": [
        "Flag",
        "Vehicle",
        "Wheel"
    ],
    "005": [
        "Wheel",
        "Person",
        "Car",
        "Land vehicle",
        "Building"
    ],
    "006": [
        "Man",
        "Person",
        "Hat",
        "Clothing",
        "Scale"
    ],
    "007": [
        "Tree",
        "Human face",
        "Man",
        "Clothing"
    ],
    "008": [
        "Plant",
        "Monkey",
        "Man",
        "Clothing"
    ],
    "009": [
        "Man",
        "Person",
        "Boy",
        "Clothing",
        "Human face"
    ],
    "010": [
        "Tower",
        "Skyscraper"
    ],
    "011": [
        "Clothing",
        "Poster",
        "Person"
    ],
    "012": [
        "Person",
        "Woman",
        "Watercraft",
        "Clothing",
        "Boat",
        "Human face"
    ],
    "013": [
        "Person",
        "Woman",
        "Man",
        "Clothing"
    ],
    "014": [
        "Clothing",
        "Woman",
        "Man",
        "Person"
    ],
    "015": [
        "Wheel",
        "Person",
        "Car",
        "Land vehicle",
        "Building"
    ],
    "016": [
        "Person",
        "Scale",
        "Man",
        "Clothing"
    ],
    "017": [
        "Desk",
        "Office building",
        "Person",
        "Woman",
        "Clothing",
        "Table",
        "Computer monitor",
        "Human face",
        "Computer keyboard"
    ],
    "018": [],
    "019": [
        "Desk",
        "Office building",
        "Glasses",
        "Person",
        "Boy",
        "Woman",
        "Clothing",
        "Mechanical fan",
        "Table",
        "Computer monitor",
        "Human face"
    ],
    "020": [
        "Desk",
        "Office building",
        "Glasses",
        "Person",
        "Boy",
        "Woman",
        "Clothing",
        "Mechanical fan",
        "Table",
        "Computer monitor",
        "Laptop",
        "Human face"
    ],
    "021": [
        "Wheel",
        "Person",
        "Man",
        "Clothing",
        "Helmet",
        "Human face",
        "Land vehicle",
        "Car"
    ],
    "022": [
        "Man",
        "Person",
        "Wheel",
        "Woman",
        "Clothing",
        "Helmet",
        "Human face"
    ],
    "023": [
        "Man",
        "Person",
        "Motorcycle",
        "Wheel",
        "Footwear",
        "Clothing",
        "Bicycle wheel",
        "Land vehicle"
    ],
    "024": [
        "Tire",
        "Footwear",
        "Person",
        "Wheel",
        "Motorcycle",
        "Man",
        "Clothing",
        "Bicycle wheel"
    ],
    "025": [
        "Man",
        "Person",
        "Poster",
        "Billboard",
        "Human face",
        "Land vehicle"
    ],
    "026": [
        "Weapon",
        "Land vehicle",
        "Person"
    ],
    "027": [
        "Tire",
        "Man",
        "Person",
        "Wheel",
        "Motorcycle",
        "Lifejacket",
        "Clothing",
        "Human face",
        "Land vehicle",
        "Car"
    ],
    "028": [
        "Wheel",
        "Person",
        "Man",
        "Clothing",
        "Helmet",
        "Car"
    ],
    "029": [
        "Footwear",
        "Person",
        "Auto part",
        "Clothing",
        "Land vehicle"
    ],
    "030": [
        "Man",
        "Motorcycle",
        "Wheel",
        "Person",
        "Clothing"
    ],
    "031": [
        "Man",
        "Person",
        "Woman",
        "Watercraft",
        "Clothing",
        "Boat"
    ],
    "032": [
        "Clothing",
        "Woman",
        "Person"
    ],
    "033": [
        "Man",
        "Person",
        "Woman",
        "Clothing",
        "Boat",
        "Skyscraper"
    ],
    "034": [
        "Dress",
        "Man",
        "Woman",
        "Clothing",
        "Shirt",
        "Human face",
        "Skyscraper"
    ],
    "035": [
        "Dress",
        "Man",
        "Woman",
        "Clothing",
        "Girl",
        "Shirt",
        "Human face",
        "Skyscraper"
    ],
    "036": [
        "Man",
        "Person",
        "Footwear",
        "Woman",
        "Clothing",
        "Dog",
        "Human face"
    ],
    "037": [
        "Clothing",
        "Human hand",
        "Human arm",
        "Person"
    ],
    "038": [
        "Animal",
        "Dog"
    ],
    "039": [
        "Dog"
    ],
    "040": [
        "Plant",
        "Wheel",
        "Dog",
        "Bicycle wheel",
        "Bicycle",
        "Land vehicle",
        "Tree"
    ],
    "041": [
        "Clothing",
        "Person"
    ],
    "042": [
        "Human hand",
        "Person"
    ],
    "043": [
        "Man",
        "Person",
        "Clothing",
        "Human hand",
        "Animal"
    ],
    "044": [
        "Plant",
        "Cattle",
        "Carnivore",
        "Dog"
    ],
    "045": [
        "Human face",
        "Dog"
    ],
    "046": [
        "Animal",
        "Carnivore",
        "Dog",
        "Plant",
        "Flower"
    ],
    "047": [
        "Animal",
        "Flowerpot",
        "Houseplant",
        "Dog",
        "Plant"
    ],
    "048": [
        "Human leg",
        "Footwear",
        "Person",
        "Dog",
        "Animal"
    ],
    "049": [
        "Dress",
        "Tower",
        "Woman",
        "Clothing",
        "Human face",
        "Skyscraper",
        "Building"
    ],
    "050": [
        "Tree",
        "Human face",
        "Man",
        "Clothing"
    ],
    "051": [
        "Tree",
        "Porch",
        "Furniture",
        "Stairs"
    ],
    "052": [
        "Man",
        "Clothing"
    ],
    "053": [
        "Tree",
        "Man",
        "Clothing"
    ],
    "054": [
        "Plant",
        "Tree",
        "Person"
    ],
    "055": [
        "Plant",
        "Boy",
        "Man",
        "Clothing"
    ],
    "056": [
        "Plant",
        "Flower"
    ],
    "057": [
        "Plant",
        "Tree",
        "Clothing"
    ],
    "058": [
        "Plant",
        "Tree"
    ],
    "059": [
        "Plant",
        "Tree"
    ],
    "060": [
        "Man",
        "Person",
        "Clothing",
        "Tree",
        "Tent"
    ],
    "061": [
        "Footwear",
        "Person",
        "Man",
        "Clothing",
        "Building"
    ],
    "062": [
        "Footwear",
        "Person",
        "Man",
        "Clothing",
        "House",
        "Human face",
        "Skyscraper",
        "Building"
    ],
    "063": [
        "Stairs",
        "Clothing",
        "Porch",
        "House",
        "Tree",
        "Building"
    ],
    "064": [
        "Plant",
        "Tree"
    ],
    "065": [
        "Wheel",
        "Person",
        "Man",
        "Motorcycle",
        "Clothing",
        "Helmet",
        "Tree"
    ],
    "066": [
        "Wheel",
        "Person",
        "Man",
        "Woman",
        "Clothing",
        "Tree"
    ],
    "067": [
        "Person",
        "Poster",
        "Tree",
        "Clothing"
    ],
    "068": [
        "Dress",
        "Man",
        "Woman",
        "Clothing",
        "Girl",
        "Human face",
        "Skyscraper"
    ],
    "069": [
        "Dress",
        "Man",
        "Woman",
        "Clothing",
        "Shirt",
        "Human face",
        "Skyscraper"
    ],
    "070": [
        "Dress",
        "Man",
        "Person",
        "Woman",
        "Clothing",
        "Shirt",
        "Human face",
        "Skyscraper"
    ],
    "071": [
        "Flower",
        "Airplane",
        "Vehicle",
        "Building"
    ],
    "072": [
        "Man",
        "Suit",
        "Person",
        "Woman",
        "Clothing",
        "Human face"
    ],
    "073": [
        "Man",
        "Suit",
        "Person",
        "Woman",
        "Clothing",
        "Human face"
    ],
    "074": [
        "Book",
        "Houseplant",
        "Shelf",
        "Poster",
        "Plant",
        "Building"
    ],
    "075": [
        "Book",
        "Houseplant",
        "Shelf",
        "Rose",
        "Plant",
        "Bottle",
        "Food"
    ],
    "076": [
        "Man",
        "Suit",
        "Person",
        "Woman",
        "Clothing",
        "Girl",
        "Human face"
    ],
    "077": [
        "Footwear",
        "Personal care",
        "Bottle",
        "Food"
    ],
    "078": [
        "Man",
        "Suit",
        "Person",
        "Woman",
        "Clothing",
        "Toy",
        "Human face"
    ],
    "079": [
        "Book",
        "Houseplant",
        "Shelf",
        "Fruit",
        "Plant",
        "Bottle"
    ],
    "080": [
        "Man",
        "Person",
        "Suit",
        "Woman",
        "Clothing",
        "Girl",
        "Human face"
    ],
    "081": [
        "Dress",
        "Man",
        "Suit",
        "Person",
        "Woman",
        "Clothing",
        "Girl",
        "Human face"
    ],
    "082": [
        "Bottle",
        "Personal care",
        "Food"
    ],
    "083": [
        "Man",
        "Suit",
        "Person",
        "Clothing",
        "Poster",
        "Plant",
        "Human face",
        "Tree"
    ],
    "084": [
        "Tie",
        "Man",
        "Suit",
        "Person",
        "Clothing",
        "Poster",
        "Plant",
        "Human face"
    ],
    "085": [
        "Man",
        "Person",
        "Suit",
        "Clothing",
        "Table",
        "Convenience store"
    ],
    "086": [
        "Man",
        "Suit",
        "Footwear",
        "Woman",
        "Clothing",
        "Human face"
    ],
    "087": [
        "Man",
        "Suit",
        "Woman",
        "Clothing",
        "Human face"
    ],
    "088": [
        "Man",
        "Saucer",
        "Person",
        "Woman",
        "Coffee cup",
        "Clothing"
    ],
    "089": [
        "Footwear",
        "Man",
        "Woman",
        "Clothing",
        "Human face"
    ],
    "090": [
        "Footwear",
        "Person",
        "Chair",
        "Snack",
        "Food"
    ],
    "091": [
        "Dress",
        "Woman",
        "Clothing",
        "Human face",
        "Food"
    ],
    "092": [
        "Dress",
        "Woman",
        "Clothing",
        "Girl",
        "Plant",
        "Human face",
        "Food"
    ],
    "093": [
        "Dress",
        "Man",
        "Person",
        "Woman",
        "Clothing",
        "Girl",
        "Human face"
    ],
    "094": [
        "Dress",
        "Woman",
        "Clothing",
        "Girl",
        "Fashion accessory",
        "Human face",
        "Train"
    ],
    "095": [
        "Train"
    ],
    "096": [
        "Man",
        "Woman",
        "Clothing",
        "Girl",
        "Human face",
        "Building"
    ],
    "097": [
        "Dairy",
        "Dessert",
        "Food"
    ],
    "098": [
        "Glasses",
        "Human face",
        "Man",
        "Clothing"
    ],
    "099": [
        "Glasses",
        "Man",
        "Television",
        "Woman",
        "Sunglasses",
        "Human face"
    ],
    "100": [
        "Book",
        "Shelf",
        "Poster"
    ],
    "101": [
        "Glasses",
        "Man",
        "Clothing",
        "Girl",
        "Human face"
    ],
    "102": [
        "Drink",
        "Boy",
        "Woman",
        "Couch",
        "Clothing",
        "Girl",
        "Table",
        "Human face",
        "Land vehicle",
        "Window"
    ],
    "103": [
        "Woman",
        "Couch",
        "Clothing",
        "Girl",
        "Table",
        "Human face",
        "Land vehicle",
        "Window"
    ],
    "104": [
        "Wheel",
        "Man",
        "Land vehicle",
        "Window",
        "Train"
    ],
    "105": [
        "Land vehicle",
        "Wheel",
        "Window",
        "Train"
    ],
    "106": [
        "Footwear",
        "Person",
        "Man",
        "Woman",
        "Clothing"
    ],
    "107": [
        "Person",
        "Woman",
        "Man",
        "Clothing"
    ],
    "108": [
        "Dress",
        "Man",
        "Woman",
        "Clothing",
        "Girl",
        "Human face",
        "Flower"
    ],
    "109": [
        "Building",
        "Wheel",
        "Person",
        "Tree",
        "Car"
    ],
    "110": [
        "Flag",
        "Toy",
        "Vehicle",
        "Airplane"
    ],
    "111": [
        "Footwear",
        "Person",
        "Man",
        "Chair",
        "Clothing"
    ],
    "112": [
        "Man",
        "Person",
        "Clothing",
        "Poster",
        "Human face"
    ],
    "113": [
        "Dress",
        "Man",
        "Footwear",
        "Person",
        "Woman",
        "Chair",
        "Clothing",
        "Table",
        "Land vehicle",
        "Umbrella"
    ],
    "114": [
        "Person",
        "Candy",
        "Food",
        "Clothing"
    ],
    "115": [
        "Tower",
        "Man",
        "Clothing",
        "Human face",
        "Land vehicle",
        "Skyscraper"
    ],
    "116": [
        "Tower",
        "Man",
        "Clothing",
        "Shirt",
        "Human face",
        "Skyscraper"
    ],
    "117": [
        "Man",
        "Person",
        "Boy",
        "Clothing",
        "Human face"
    ],
    "118": [
        "Poster",
        "Human hand"
    ],
    "119": [
        "Man",
        "Person",
        "Clothing",
        "Table",
        "Human face"
    ],
    "120": [
        "Man",
        "Clothing",
        "House",
        "Plant",
        "Human face",
        "Window"
    ],
    "121": [
        "Plastic bag",
        "Food",
        "Snack"
    ],
    "122": [
        "Person",
        "Clothing"
    ],
    "123": [
        "Clothing",
        "Flower",
        "Human hand",
        "Person"
    ],
    "124": [
        "Man",
        "Person",
        "Chair",
        "Clothing",
        "Human face"
    ],
    "125": [
        "Dress",
        "Woman",
        "Clothing",
        "Girl",
        "Poster",
        "Human face"
    ],
    "126": [
        "Dress",
        "Woman",
        "Clothing",
        "Girl",
        "Poster",
        "Human face"
    ],
    "127": [
        "Man",
        "Person",
        "Woman",
        "Chair",
        "Clothing",
        "Table",
        "Human face"
    ],
    "128": [
        "Man",
        "Person",
        "Hat",
        "Chair",
        "Clothing",
        "Girl",
        "Human face"
    ],
    "129": [
        "Man",
        "Hat",
        "Person",
        "Chair",
        "Clothing",
        "Crown",
        "Human face"
    ],
    "130": [
        "Man",
        "Person",
        "Hat",
        "Chair",
        "Clothing",
        "Table",
        "Laptop",
        "Human face"
    ],
    "131": [
        "Book",
        "Pen",
        "Human hand",
        "Office supplies"
    ],
    "132": [
        "Man",
        "Person",
        "Woman",
        "Clothing",
        "Human face"
    ],
    "133": [
        "Human face",
        "Woman",
        "Man",
        "Clothing"
    ],
    "134": [
        "Man",
        "Person",
        "Woman",
        "Chair",
        "Clothing",
        "Table",
        "Human face"
    ],
    "135": [
        "Office building",
        "Man",
        "Person",
        "Hat",
        "Clothing",
        "Laptop",
        "Human face"
    ],
    "136": [
        "Office building",
        "Man",
        "Person",
        "Woman",
        "Clothing",
        "Table",
        "Laptop",
        "Human face"
    ],
    "137": [
        "Man",
        "Person",
        "Chair",
        "Clothing",
        "Building"
    ],
    "138": [
        "Glasses",
        "Tower",
        "Man",
        "Clothing",
        "Shirt",
        "Human face",
        "Skyscraper"
    ],
    "139": [
        "Glasses",
        "Tower",
        "Man",
        "Clothing",
        "Shirt",
        "Human face",
        "Skyscraper"
    ],
    "140": [
        "Laptop"
    ],
    "141": [
        "Office building",
        "Person",
        "Printer",
        "Boy",
        "Chair",
        "Picture frame",
        "Clothing",
        "Human face"
    ],
    "142": [
        "Human face",
        "Boy",
        "Curtain"
    ],
    "143": [
        "Office building",
        "Man",
        "Person",
        "Printer",
        "Boy",
        "Clothing",
        "Human face"
    ],
    "144": [
        "Desk",
        "Office building",
        "Person",
        "Printer",
        "Boy",
        "Office supplies",
        "Clothing",
        "Table",
        "Human face"
    ],
    "145": [
        "Book",
        "Boy",
        "Human nose",
        "Clothing",
        "Human face"
    ],
    "146": [
        "Human face",
        "Boy",
        "Human nose"
    ],
    "147": [
        "Desk",
        "Office building",
        "Person",
        "Printer",
        "Boy",
        "Clothing",
        "Laptop",
        "Human face"
    ],
    "148": [
        "Dress",
        "Woman",
        "Clothing",
        "Girl",
        "Poster",
        "Human face"
    ],
    "149": [
        "Dress",
        "Woman",
        "Clothing",
        "Girl",
        "Poster",
        "Human face"
    ],
    "150": [
        "Person",
        "Human face",
        "Man",
        "Clothing"
    ],
    "151": [
        "Glasses",
        "Man",
        "Person",
        "Clothing",
        "Poster",
        "Human face"
    ],
    "152": [
        "Person",
        "Human face",
        "Man",
        "Clothing"
    ],
    "153": [
        "Human face",
        "Shirt",
        "Man",
        "Clothing"
    ],
    "154": [
        "Human face",
        "Shirt",
        "Man",
        "Clothing"
    ],
    "155": [
        "Man",
        "Person",
        "Clothing",
        "Shirt",
        "Poster",
        "Human face"
    ],
    "156": [
        "Man",
        "Person",
        "Chair",
        "Clothing",
        "Furniture",
        "Shirt",
        "Human face"
    ],
    "157": [
        "Clothing",
        "Human hand",
        "Person"
    ],
    "158": [
        "Man",
        "Person",
        "Clothing",
        "Shirt",
        "Human face",
        "Human head"
    ],
    "159": [
        "Man",
        "Person",
        "Clothing",
        "Shirt",
        "Human head",
        "Human face",
        "Whiteboard"
    ],
    "160": [
        "Person",
        "Human face",
        "Man",
        "Clothing"
    ],
    "161": [
        "Person",
        "Human face",
        "Man",
        "Clothing"
    ],
    "162": [
        "Tower",
        "Man",
        "Clothing",
        "Human face",
        "Land vehicle",
        "Skyscraper"
    ],
    "163": [
        "Tower",
        "Man",
        "Clothing",
        "Human face",
        "Skyscraper"
    ],
    "164": [
        "Dress",
        "Woman",
        "Clothing",
        "Girl",
        "Poster",
        "Human face"
    ],
    "165": [
        "Dress",
        "Woman",
        "Television",
        "Clothing",
        "Girl",
        "Poster",
        "Human face"
    ],
    "166": [
        "Wheel",
        "Motorcycle",
        "Chair",
        "Plant",
        "Land vehicle",
        "Tree",
        "Umbrella"
    ],
    "167": [
        "Horse",
        "Person",
        "Clothing",
        "Helmet",
        "Animal",
        "Land vehicle",
        "Tree"
    ],
    "168": [
        "Man",
        "Person",
        "Clothing",
        "Human face",
        "Land vehicle",
        "Tree"
    ],
    "169": [
        "Human hand",
        "Person"
    ],
    "170": [
        "Book",
        "Poster",
        "Human hand",
        "Person"
    ],
    "171": [
        "Person",
        "Human hand",
        "Computer keyboard",
        "Laptop",
        "Mobile phone"
    ],
    "172": [
        "Person",
        "Book",
        "Drink",
        "Tablet computer",
        "Poster",
        "Toy"
    ],
    "173": [
        "Clothing",
        "Person"
    ],
    "174": [
        "Poster"
    ],
    "175": [
        "Human face",
        "Poster",
        "Clothing",
        "Person"
    ],
    "176": [
        "Curtain",
        "Woman",
        "Chair",
        "Clothing",
        "Shelf",
        "Table",
        "Girl",
        "House",
        "Human face",
        "Window"
    ],
    "177": [
        "Man",
        "Person",
        "Hat",
        "Woman",
        "Clothing",
        "Human face"
    ],
    "178": [
        "Person"
    ],
    "179": [
        "Glasses",
        "Man",
        "Person",
        "Clothing",
        "Door",
        "Human face",
        "Window"
    ],
    "180": [
        "Man",
        "Person",
        "Woman",
        "Clothing",
        "Girl",
        "Poster",
        "Human face",
        "Building"
    ],
    "181": [
        "Tower",
        "Man",
        "Clothing",
        "Human face",
        "Skyscraper"
    ],
    "182": [
        "Tower",
        "Man",
        "Clothing",
        "Human face",
        "Skyscraper"
    ],
    "183": [
        "Wheel",
        "Person",
        "Clothing",
        "Bicycle wheel",
        "Bicycle",
        "Land vehicle",
        "Building"
    ],
    "184": [
        "Vehicle",
        "Clothing"
    ],
    "185": [
        "Toy",
        "Clothing"
    ],
    "186": [
        "Wheel",
        "Person",
        "Clothing",
        "Bicycle wheel",
        "Bicycle",
        "Tree",
        "Building"
    ],
    "187": [
        "Man",
        "Person",
        "Van",
        "Woman",
        "Clothing",
        "Human face"
    ],
    "188": [
        "Man",
        "Hat",
        "Person",
        "Woman",
        "Clothing",
        "Girl",
        "Human face"
    ],
    "189": [
        "Human face",
        "Man",
        "Person"
    ],
    "190": [
        "Plastic bag"
    ],
    "191": [
        "Flag",
        "Clothing"
    ],
    "192": [
        "Flag"
    ],
    "193": [
        "Boat",
        "Wheel",
        "Person"
    ],
    "194": [
        "Helicopter",
        "Man",
        "Person",
        "Clothing",
        "Boat",
        "Helmet"
    ],
    "195": [
        "Man",
        "Person",
        "Clothing",
        "Boat",
        "Helmet"
    ],
    "196": [
        "Man",
        "Person",
        "Boy",
        "Clothing",
        "Human face"
    ],
    "197": [
        "Man",
        "Person",
        "Human arm",
        "Clothing",
        "Human hand"
    ],
    "198": [
        "Tower",
        "Man",
        "Clothing",
        "Human face",
        "Land vehicle",
        "Skyscraper",
        "Car"
    ],
    "199": [
        "Tower",
        "Man",
        "Clothing",
        "Human face",
        "Land vehicle",
        "Skyscraper"
    ],
    "200": [
        "Tower",
        "Man",
        "Clothing",
        "Shirt",
        "Human face",
        "Skyscraper"
    ],
    "201": [
        "Man",
        "Person",
        "Clothing",
        "Human face",
        "Skyscraper"
    ],
    "202": [
        "Man",
        "Person",
        "Clothing",
        "Boat",
        "Vehicle"
    ],
    "203": [
        "Man",
        "Person",
        "Clothing",
        "Boat",
        "Helmet"
    ],
    "204": [
        "Clothing",
        "Man",
        "Person"
    ],
    "205": [
        "Dress",
        "Woman",
        "Clothing",
        "Girl",
        "Poster",
        "Human face"
    ],
    "206": [
        "Dress",
        "Woman",
        "Clothing",
        "Girl",
        "Poster",
        "Human face"
    ],
    "207": [
        "Dress",
        "Woman",
        "Television",
        "Clothing",
        "Girl",
        "Poster",
        "Human face"
    ],
    "208": [
        "Wheel",
        "Van",
        "Land vehicle",
        "Tree",
        "Car"
    ],
    "209": [
        "Land vehicle",
        "Tree",
        "Car"
    ],
    "210": [
        "Person",
        "Land vehicle",
        "Wheel",
        "Car"
    ],
    "211": [
        "Tire",
        "Man",
        "Wheel",
        "Van",
        "Taxi",
        "Clothing",
        "Car",
        "Human face",
        "Truck"
    ],
    "212": [
        "Tire",
        "Wheel",
        "Man",
        "Clothing",
        "Human face",
        "Car"
    ],
    "213": [
        "Wheel",
        "Person",
        "Woman",
        "Taxi",
        "Clothing",
        "Vehicle registration plate",
        "Car"
    ],
    "214": [
        "Tie",
        "Man",
        "Person",
        "Suit",
        "Clothing",
        "Human face"
    ],
    "215": [
        "Human face",
        "Tie",
        "Man",
        "Suit"
    ],
    "216": [
        "Wheel",
        "Person",
        "Land vehicle",
        "Bus",
        "Building"
    ],
    "217": [
        "Skyscraper",
        "Tree",
        "Street light"
    ],
    "218": [
        "Stairs",
        "Person",
        "Watercraft",
        "Tree",
        "Train"
    ],
    "219": [
        "Handbag",
        "Man",
        "Television",
        "Clothing",
        "Mirror",
        "Vehicle",
        "Train"
    ],
    "220": [
        "Human face",
        "Woman",
        "Man",
        "Clothing"
    ],
    "221": [
        "Poster"
    ],
    "222": [
        "Wheel",
        "Van",
        "Taxi",
        "Car",
        "Land vehicle",
        "Truck"
    ],
    "223": [
        "Land vehicle",
        "Truck",
        "Wheel",
        "Car"
    ],
    "224": [
        "Person",
        "Wheel",
        "Car"
    ],
    "225": [
        "Tower",
        "Man",
        "Clothing",
        "Shirt",
        "Human face",
        "Skyscraper"
    ],
    "226": [
        "Glasses",
        "Tower",
        "Man",
        "Clothing",
        "Shirt",
        "Human face",
        "Skyscraper"
    ],
    "227": [
        "Glasses",
        "Tower",
        "Man",
        "Clothing",
        "Shirt",
        "Human face",
        "Skyscraper"
    ],
    "228": [
        "Glasses",
        "Tower",
        "Man",
        "Clothing",
        "Shirt",
        "Human face",
        "Skyscraper"
    ],
    "229": [
        "Human face",
        "Woman"
    ],
    "230": [
        "Human face",
        "Woman",
        "Clothing",
        "Fashion accessory"
    ],
    "231": [
        "Dress",
        "Man",
        "Suit",
        "Woman",
        "Human face"
    ],
    "232": [
        "Dress",
        "Man",
        "Suit",
        "Woman",
        "Human face"
    ],
    "233": [
        "Human ear",
        "Boy",
        "Clothing",
        "Girl",
        "Human hand",
        "Human face",
        "Human head"
    ],
    "234": [
        "Man",
        "Person",
        "Woman",
        "Clothing",
        "Table",
        "Human face",
        "Food"
    ],
    "235": [
        "Man",
        "Person",
        "Boy",
        "Woman",
        "Clothing",
        "Girl",
        "Table",
        "Human face",
        "Food"
    ],
    "236": [
        "Man",
        "Woman",
        "Clothing",
        "Girl",
        "Human face"
    ],
    "237": [
        "Human face",
        "Woman",
        "Man",
        "Clothing"
    ],
    "238": [
        "Dress",
        "Man",
        "Person",
        "Woman",
        "Clothing",
        "Girl",
        "Toy",
        "Helmet",
        "Human face"
    ],
    "239": [
        "Dress",
        "Woman",
        "Clothing",
        "Dessert",
        "Human face",
        "Food"
    ],
    "240": [
        "Dress",
        "Woman",
        "Clothing",
        "Human face",
        "Food"
    ],
    "241": [
        "Kitchen utensil",
        "Person",
        "Frying pan",
        "Toy",
        "Human face",
        "Tableware",
        "Human head"
    ],
    "242": [
        "Person",
        "Human face",
        "Toy",
        "Clothing"
    ],
    "243": [
        "Fruit",
        "Pear"
    ],
    "244": [
        "Man",
        "Person",
        "Clothing",
        "Toy",
        "Human face"
    ],
    "245": [
        "Man",
        "Hat",
        "Person",
        "Wheel",
        "Clothing",
        "Toy",
        "Human face"
    ],
    "246": [
        "Human face",
        "Man",
        "Clothing"
    ],
    "247": [
        "Kitchen utensil",
        "Person",
        "Frying pan",
        "Toy",
        "Human face",
        "Tableware"
    ],
    "248": [
        "Computer keyboard",
        "Auto part",
        "Food"
    ],
    "249": [
        "Human face",
        "Toy",
        "Camera",
        "Person"
    ],
    "250": [
        "Man",
        "Footwear",
        "Woman",
        "Clothing",
        "Table",
        "Box",
        "Bowling equipment"
    ],
    "251": [
        "Toy"
    ],
    "252": [
        "Man",
        "Person",
        "Clothing",
        "Furniture",
        "Shelf",
        "Table",
        "Toy",
        "Human head"
    ],
    "253": [
        "Man",
        "Person",
        "Woman",
        "Clothing",
        "Human face"
    ],
    "254": [
        "Human face",
        "Vase",
        "Toy"
    ],
    "255": [
        "Human face",
        "Human ear",
        "Man",
        "Clothing"
    ],
    "256": [
        "Coin",
        "Egg",
        "Flower",
        "Food"
    ],
    "257": [
        "Table",
        "Toy",
        "Human face",
        "Drink"
    ],
    "258": [
        "Dress",
        "Woman",
        "Clothing",
        "Girl",
        "Human face"
    ],
    "259": [
        "Dress",
        "Man",
        "Person",
        "Woman",
        "Clothing",
        "Human face",
        "Flower"
    ],
    "260": [
        "Person",
        "Woman",
        "Clothing",
        "Flower",
        "Tree"
    ],
    "261": [
        "Flower"
    ],
    "262": [
        "Clothing",
        "Woman",
        "Man",
        "Person"
    ],
    "263": [
        "Flower"
    ],
    "264": [
        "Flower",
        "Rose",
        "Houseplant"
    ],
    "265": [
        "Man",
        "Person",
        "Clothing",
        "Human face",
        "Flower"
    ],
    "266": [
        "Flower",
        "Rose"
    ],
    "267": [
        "Plant",
        "Flower"
    ],
    "268": [
        "Flower"
    ],
    "269": [
        "Man",
        "Person",
        "Boy",
        "Woman",
        "Clothing",
        "Girl"
    ],
    "270": [
        "Flower",
        "Rose",
        "Houseplant"
    ],
    "271": [
        "Clothing",
        "Flower",
        "Tree",
        "Person"
    ],
    "272": [
        "Man",
        "Person",
        "Watercraft",
        "Clothing",
        "Boat",
        "Airplane",
        "Skyscraper",
        "Vehicle"
    ],
    "273": [
        "Tower",
        "Man",
        "Person",
        "Window",
        "Clothing",
        "House",
        "Human face",
        "Skyscraper",
        "Tree"
    ],
    "274": [
        "Trousers",
        "Man",
        "Clothing",
        "Shirt",
        "Human face",
        "Skyscraper"
    ],
    "275": [
        "Boy",
        "Footwear",
        "Man",
        "Clothing"
    ],
    "276": [
        "Man",
        "Person",
        "Football",
        "Clothing",
        "Human face"
    ],
    "277": [
        "Footwear",
        "Person",
        "Man",
        "Woman",
        "Clothing",
        "Human face"
    ],
    "278": [
        "Footwear",
        "Person",
        "Man",
        "Clothing",
        "Human face"
    ],
    "279": [
        "Sports uniform",
        "Glasses",
        "Footwear",
        "Man",
        "Person",
        "Clothing",
        "Human face"
    ],
    "280": [
        "Man",
        "Person",
        "Tree",
        "Footwear",
        "Football",
        "Clothing",
        "Window",
        "Building"
    ],
    "281": [
        "Human face",
        "Man",
        "Clothing"
    ],
    "282": [
        "Human face",
        "Football",
        "Man",
        "Clothing"
    ],
    "283": [
        "Boy",
        "Footwear",
        "Man",
        "Person"
    ],
    "284": [
        "Footwear",
        "Man",
        "Person",
        "Boy",
        "Clothing"
    ],
    "285": [
        "Man",
        "Boy",
        "Woman",
        "Clothing",
        "Human face"
    ],
    "286": [
        "Man",
        "Person",
        "Clothing",
        "Shirt",
        "Human face"
    ],
    "287": [
        "Tire",
        "Wheel",
        "Person",
        "Man",
        "Clothing",
        "Shirt",
        "Human face",
        "Car"
    ],
    "288": [
        "Land vehicle",
        "Wheel",
        "Car"
    ],
    "289": [
        "Tire",
        "Wheel",
        "Car"
    ],
    "290": [
        "Auto part",
        "Car"
    ],
    "291": [
        "Man",
        "Person",
        "Clothing",
        "Helmet",
        "Human face"
    ],
    "292": [
        "Land vehicle",
        "Vehicle"
    ],
    "293": [
        "Land vehicle",
        "Airplane",
        "Vehicle",
        "Car"
    ],
    "294": [
        "Wheel",
        "Car"
    ],
    "295": [
        "Land vehicle",
        "Tree",
        "Car"
    ],
    "296": [
        "Dress",
        "Man",
        "Person",
        "Woman",
        "Clothing",
        "Girl",
        "Human face"
    ],
    "297": [
        "Dress",
        "Woman",
        "Clothing",
        "Human face",
        "Swimwear"
    ],
    "298": [
        "Dress",
        "Man",
        "Woman",
        "Clothing",
        "Girl",
        "Human face",
        "Swimwear"
    ],
    "299": [
        "Man",
        "Woman",
        "Clothing",
        "Girl",
        "Human face",
        "Swimwear",
        "Building"
    ],
    "300": [
        "Sports uniform",
        "Man",
        "Woman",
        "Clothing",
        "Human face"
    ],
    "301": [
        "Human face",
        "Window",
        "Man"
    ],
    "302": [
        "Footwear",
        "Man",
        "Suit",
        "Woman",
        "Clothing",
        "Human face",
        "Swimwear"
    ],
    "303": [
        "Footwear",
        "Man",
        "Woman",
        "Girl",
        "Human face",
        "Swimwear"
    ],
    "304": [
        "Sports uniform",
        "Man",
        "Woman",
        "Clothing",
        "Girl",
        "Human face"
    ],
    "305": [
        "Man",
        "Person",
        "Clothing",
        "Shirt",
        "Human face"
    ],
    "306": [
        "Man",
        "Person",
        "Clothing",
        "Coin",
        "Shirt",
        "Fashion accessory",
        "Human face"
    ],
    "307": [
        "Man",
        "Person",
        "Clothing",
        "Coin",
        "Shirt",
        "Human face"
    ],
    "308": [
        "Man",
        "Person",
        "Clothing",
        "Shirt",
        "Human face"
    ],
    "309": [
        "Man",
        "Person",
        "Clothing",
        "Shirt",
        "Human face"
    ],
    "310": [
        "Man",
        "Person",
        "Suit",
        "Clothing",
        "Poster",
        "Human face",
        "Food"
    ],
    "311": [
        "Man",
        "Person",
        "Suit",
        "Clothing",
        "Human face"
    ],
    "312": [
        "Coin",
        "Fashion accessory",
        "Earrings"
    ],
    "313": [
        "Man",
        "Suit",
        "Person",
        "Clothing",
        "Door",
        "Human face",
        "Food"
    ],
    "314": [
        "Man",
        "Person",
        "Woman",
        "Clothing",
        "Human face"
    ],
    "315": [
        "Footwear",
        "Man",
        "Clothing"
    ],
    "316": [
        "Footwear",
        "Man",
        "Person"
    ],
    "317": [
        "Boy",
        "Footwear",
        "Man"
    ],
    "318": [
        "Book",
        "Vase"
    ],
    "319": [
        "House",
        "Table",
        "Window",
        "Building"
    ],
    "320": [
        "Office building",
        "Furniture",
        "House",
        "Window",
        "Building"
    ],
    "321": [
        "Dress",
        "Footwear",
        "Person",
        "Man",
        "Woman",
        "Clothing",
        "Human face"
    ],
    "322": [
        "Man",
        "Person",
        "Woman",
        "Watercraft",
        "Clothing",
        "Boat"
    ],
    "323": [
        "Airplane",
        "Tree"
    ],
    "324": [
        "Plant",
        "Tree"
    ],
    "325": [
        "Wheel",
        "Person",
        "Truck",
        "Vehicle",
        "Car"
    ],
    "326": [
        "Plant",
        "Poster",
        "Tree"
    ],
    "327": [
        "Mobile phone"
    ],
    "328": [
        "Plant",
        "Person",
        "Man",
        "Clothing"
    ],
    "329": [
        "Person",
        "Tank",
        "Clothing",
        "Land vehicle",
        "Vehicle"
    ],
    "330": [
        "Tank",
        "Airplane",
        "Vehicle"
    ],
    "331": [
        "Land vehicle",
        "Vehicle",
        "Tree"
    ],
    "332": [
        "Man",
        "Person",
        "Woman",
        "Watercraft",
        "Clothing",
        "Human face"
    ],
    "333": [
        "Man",
        "Person",
        "Woman",
        "Clothing",
        "Boat",
        "Human face"
    ],
    "334": [
        "Man",
        "Person",
        "Woman",
        "Clothing",
        "Human face"
    ]
}