{
    "006.jpg": "tin ghinh",
    "007.jpg": "y oy caied tin ghinh 4 c no luc giam phat thai tu giao thong as",
    "016.jpg": "htv1 truc tiep be mac le hoi lang sen 2024",
    "035.jpg": "eu hanh voi ao dai hoa sen",
    "053.jpg": "ee 5 400 s6 lueng bac tai tai tp hom so luieng bac taidat quam tam chuong trinh diem tin dung so lueng xe may dien da bani giao 36 lieu tir 01022024 den 31032024",
    "061.jpg": "i ee transportation solutions aen a 052024 0839 1939 wena a thank doante hem lal",
    "062.jpg": "chuven do giao eal ta te ho chi mine spsing ceremony the transition ctric transportation solutions in ho chi minh city av 08301939 thank born te hoy lau 3 outhunion ho",
    "079.jpg": "f 2s bee ulmer ts ns oe",
    "083.jpg": "a oe fe iis oa",
    "084.jpg": "ngu dan khanh hoa che cap treo chuyen hang ra khu neo dau tau thuyen",
    "137.jpg": "a f ci ane ih i c be",
    "143.jpg": "y",
    "147.jpg": "a aa a pd",
    "158.jpg": "y",
    "159.jpg": "tep theo oew dong nai chay cong ty san xuat giay dep 6 dong nai",
    "178.jpg": "ry tphcm bat nghi pham gia danh canh sat hinh su kiem tra xe cuong boat tien",
    "185.jpg": "d2lai",
    "187.jpg": "wa",
    "191.jpg": "dong nai chay cong ty san xuat giay dep khu cong nghiep song may trang bom",
    "201.jpg": "ry i dei eo nguoi dan ong tu vong nghi do roi tu cay cao xuong dat a ae",
    "213.jpg": "cong cu kich dien",
    "221.jpg": "da nang gia website danh bac mes lua dao 300 nguoi cho chi trong vai ngay",
    "222.jpg": "rr pootoeoe a ar cd a9 1 oe ce ean pa ome seg a ay oct ae",
    "224.jpg": "aaa fee ll seieeenen",
    "242.jpg": "phien quan tan cong miennam kashmir trugc vong 5 bo phieu bau cu qugc ho an bo",
    "243.jpg": "at 4 5g ris ge fats sr phien quai quan tan eons mien nam kashmir truoc vong 5 bo phieu bau cu qu6c hoi an do",
    "253.jpg": "oars"
}