[
    {
        "start_time": 10,
        "end_time": 20,
        "text": "chào mừng quý vị đến với chương trình 60 giây của Đại truyền hình thành phố Hồ Chí Minh chương trình Sáng nay có những",
        "img_path": [
            "003.jpg",
            "004.jpg",
            "005.jpg",
            "006.jpg"
        ]
    },
    {
        "start_time": 20,
        "end_time": 30,
        "text": "thông tin nổi bật sau kiến nghị mở rộng cao tốc từ thành phố Hồ Chí Minh đến Long Thạnh lên 10 làn xe đóng một ngư dân được cứu sống",
        "img_path": [
            "007.jpg"
        ]
    },
    {
        "start_time": 30,
        "end_time": 40,
        "text": "trong vụ bốn tàu cá ng dân Quảng Bình bị chimm ngân hàng nhà nước tổ chức thành công Phiên đấu thầu vạn miếng với tám đơn vị trúng thầu hơn 220 công nhân nhập",
        "img_path": [
            "008.jpg",
            "009.jpg"
        ]
    },
    {
        "start_time": 40,
        "end_time": 50,
        "text": "viện với biểu hiện ngộ độc thực phẩm tại Vĩnh Phúc thưa quý vị Ủy ban nhân dân tỉnh",
        "img_path": [
            "010.jpg",
            "011.jpg"
        ]
    },
    {
        "start_time": 50,
        "end_time": 60,
        "text": "Đồng Nai ngày 14 tháng 5 cho biết đã có văn bản kiến nghị chính phủ lựa chọn phương án mở rộng cao tốc từ thành phố Hồ Chí Minh đến huyện Long Thành lên 10 làn",
        "img_path": [
            "012.jpg"
        ]
    },
    {
        "start_time": 60,
        "end_time": 70,
        "text": "xe hiện Trung ương đang đề tra hai phương án mở rộng đoạn cao tốc này trong đó phương án một đoạn tuyến được mở rộng với chiều dài gần 22 km m 8 làn xe tổng",
        "img_path": [
            "013.jpg",
            "014.jpg"
        ]
    },
    {
        "start_time": 70,
        "end_time": 80,
        "text": "mức đầu tư gần 14.300 tỷ đồng phương án ha Mở trộng với quy mô 10 làn xe tổng mức đầu tư trên 15.600 tỷ đồng Phương án",
        "img_path": [
            "015.jpg",
            "016.jpg"
        ]
    },
    {
        "start_time": 80,
        "end_time": 90,
        "text": "1 chủ yếu sử dụng vốn ngoài ngân sách phương án hai vốn ngân sách chiếm đa số tỉnh Đồng Nai cho rằng phương án hai có tổng mức đầu tư tăng không nhiều chỉ khoảng 1300 tỷ đồng so với Phương án 1",
        "img_path": [
            "017.jpg"
        ]
    },
    {
        "start_time": 90,
        "end_time": 100,
        "text": "việc mở trò Một Lần theo đúng quy hoạch mang lại nhiều lợi ích tăng hiệu quả khai thác tránh được tình trạng đầu tư nhiều lần ca tốc thành phố Hồ Chí Minh",
        "img_path": [
            "018.jpg",
            "019.jpg"
        ]
    },
    {
        "start_time": 100,
        "end_time": 110,
        "text": "dầu dây có chiều dài 55 km quy mô bốn làn xe được khai thác vào năm 2016 những năm gần đây tuyến đường này quá tải trầm trọng thường xuyên xảy ra",
        "img_path": [
            "020.jpg",
            "021.jpg"
        ]
    },
    {
        "start_time": 110,
        "end_time": 120,
        "text": "ác tắc liên quan đến vụ bốn tàu cá của Ngư dân Quảng Bình gặp nạn trên biển ngày 14 tháng 5 đồn biên phòng Cửa khẩu cản danh Bộ đội Biên phòng tỉnh Quảng Bình đã",
        "img_path": [
            "022.jpg",
            "023.jpg",
            "024.jpg"
        ]
    },
    {
        "start_time": 120,
        "end_time": 130,
        "text": "tiếp nhận ngư dân Phạm Bá Dung sinh năm 1971 trú huyện Quảng Trạch là thuyền viên trên tàu qb 9876 TS",
        "img_path": [
            "025.jpg"
        ]
    },
    {
        "start_time": 130,
        "end_time": 140,
        "text": "hiện sức khỏe của anh Phạm Bá dung bình thường động viên phòng cửa khẩu cản Danh cũng đã tặng quà các thuyền viên tàu cá Q b98 770 TS vì đã tích cực cứu vớt các",
        "img_path": [
            "026.jpg",
            "027.jpg"
        ]
    },
    {
        "start_time": 140,
        "end_time": 150,
        "text": "thuyền viên gặp nạn trên biển như đã đưa tin từ ngày 1 đến ngày 3 tháng 5 trong lúc đánh cá trên biển bốn tàu cá của tỉnh Quảng Bình gặp Dong lốc trong đó có",
        "img_path": [
            "028.jpg"
        ]
    },
    {
        "start_time": 150,
        "end_time": 160,
        "text": "ba tàu bị chìm Một tàu mất liên lạc đến chiều ngày 14 tháng 5 lực lượng chức năng và các tàu cá trên biển đã cứu vớt được 13 người và thiể tr tổng số 24",
        "img_path": [
            "029.jpg",
            "030.jpg"
        ]
    },
    {
        "start_time": 160,
        "end_time": 170,
        "text": "thuyền viên mất tích hiện lực lượng chức năng đang tiếp tục thông báo kêu gọi các phương tiện hoạt động trên biển hỗ trợ tìm kiếm 10 ngư dân đang mất tích chưa liên lạc",
        "img_path": [
            "031.jpg"
        ]
    },
    {
        "start_time": 170,
        "end_time": 180,
        "text": "được được Phát hiện khối u buồn trứng kèm BP nữ Bệnh nhân được chỉ định phẫu thuật Tuy nhiên bệnh nhân không điều trị mà về uống thuốc theo người quen Bách",
        "img_path": [
            "032.jpg",
            "033.jpg"
        ]
    },
    {
        "start_time": 180,
        "end_time": 190,
        "text": "bảo trong gần 1 năm ngày 14 tháng 5 bệnh viện ung bứu Hà Nội thông tin về ca bệnh đặc biệt cứu sống người phụ nữ nguy kịch vì có khối u buồn trứng khổng lồ",
        "img_path": [
            "034.jpg",
            "035.jpg"
        ]
    },
    {
        "start_time": 190,
        "end_time": 200,
        "text": "bệnh nhân 63 tuổi nhập diện lại trong tình trạng nghiêm trọng cân nặng sa sút nhanh chóng chỉ trong vòng 1 tháng cái bác sĩ bệnh viện ung bú Hà Nội đã nhanh chóng tiến hành phẫu thuật phối hợp đà",
        "img_path": [
            "036.jpg"
        ]
    },
    {
        "start_time": 200,
        "end_time": 210,
        "text": "chuyền khoa trên nền bệnh lý tim mạch đặc biệt nguy hiểm với khối u bụng trứng kích thước cực lớn nặng gần 3 kg các bác sĩ khuyến cáo ung thư bụng trứng là bệnh",
        "img_path": [
            "037.jpg",
            "038.jpg"
        ]
    },
    {
        "start_time": 210,
        "end_time": 220,
        "text": "khó phòng ngừa khó phát hiện sớm vì bụng trứng là cơ quan nằm sâu trong tiểu khung các triệu chứng thường âm thầm mơ hồ không đặt hiệu Dễ nhầm lẫn với các bệnh nội phụ khá khi triệu chứng đã rõ",
        "img_path": [
            "039.jpg"
        ]
    },
    {
        "start_time": 220,
        "end_time": 230,
        "text": "bệnh thường ở giai đoạn muồn một Shiper ở Đà Nẵng đã bị trộm lấy mất xe máy hình ảnh chàng trai nghèo khó",
        "img_path": [
            "040.jpg",
            "041.jpg"
        ]
    },
    {
        "start_time": 230,
        "end_time": 240,
        "text": "được người lạ đưa lên mạng và sau đó Câu chuyện đã có một cái kết có hậu một ví dụ về nghĩa cử cao đẹp xuất phát từ tình người giữa thời buổi cuộc sống nhiều bon chen hối",
        "img_path": [
            "042.jpg",
            "043.jpg"
        ]
    },
    {
        "start_time": 240,
        "end_time": 250,
        "text": "hạ do gia đình khó khăn Ba Bị tâm thầ nên anh Đào Duy Long thương nhận đơn bên ngoài sao gi làm để kiếm thêm thu nhập giờ ngày 10 tháng khi vừa chợp mắt",
        "img_path": [
            "044.jpg",
            "045.jpg",
            "046.jpg"
        ]
    },
    {
        "start_time": 250,
        "end_time": 260,
        "text": "tạm ngoại đường thì bị lấy mất xe anh đi bộ 3 km về nhà trọ trên đường anh ghé vào quán ăn nơi Mẹ đang rửa chén thuê lúc này một số nhân viên ở quán ăn đã",
        "img_path": [
            "047.jpg",
            "048.jpg"
        ]
    },
    {
        "start_time": 260,
        "end_time": 270,
        "text": "nghe được câu chuyện nên chụp hình đang lên mạng sau khi câu chuyện của Long được chia sẻ nhiều người đã liên hệ để gửi tiền giúp anh mua lại chiếc xe mới",
        "img_path": [
            "049.jpg"
        ]
    },
    {
        "start_time": 270,
        "end_time": 280,
        "text": "sáng 12 tháng 5 một Mạnh Thường Quân còn tặng cho Long một chiếc xe mới câu chuyện là hình ảnh thân thương đẹp lum Linh về mảnh đất con người đà nặng",
        "img_path": [
            "050.jpg",
            "051.jpg"
        ]
    },
    {
        "start_time": 280,
        "end_time": 290,
        "text": "nng sáng 14 tháng 5 Ngân hàng Nhà nước đã tổ chức thành công Phiên đấu thầu vạn",
        "img_path": [
            "052.jpg"
        ]
    },
    {
        "start_time": 290,
        "end_time": 300,
        "text": "miếng với tám đơn vị trúng thầu 81 lô tương ứng 8100 lượng Theo đó giá trúng thầu thấp nhất là 87,72 triệu đồng một lượng giá trúng thầu cao nhất là 87,74",
        "img_path": [
            "053.jpg",
            "054.jpg"
        ]
    },
    {
        "start_time": 300,
        "end_time": 310,
        "text": "triệu đồng một lượng như vậy khối lượng vàng trúng thầu sáng qua là cao nhất trong ba Phiên đấu thầu vàng biến thành công được ngân hàng nhà nước tổ",
        "img_path": [
            "055.jpg"
        ]
    },
    {
        "start_time": 310,
        "end_time": 320,
        "text": "chức trong phần sau xe tải trọng trên 24 tấn sẽ bị cấm Qua Cầu Rạch miểu trong khung giờ cố",
        "img_path": [
            "056.jpg",
            "057.jpg"
        ]
    },
    {
        "start_time": 320,
        "end_time": 330,
        "text": "định công an Vĩnh Long và Hậu Giang phá nhanh vụ án Bắc cóc đòi 10 tỷ đồng tiền",
        "img_path": [
            "058.jpg",
            "059.jpg"
        ]
    },
    {
        "start_time": 330,
        "end_time": 340,
        "text": "chuột xe tải nặng tải trọng trên 24 tấn sẽ bị cấm Qua Cầu Rạch miểu trong khung giờ cố định các ngày trong tuần dự kiến việc điểm sẽ thực hiện trong 15 ngày",
        "img_path": [
            "060.jpg",
            "061.jpg"
        ]
    },
    {
        "start_time": 340,
        "end_time": 350,
        "text": "trước khi đưa ra lệnh cấm chính thức kéo dài cho đến khi cầu Rạch miểu ha thi công xong theo đó việc cắm xe tải ba trục trở",
        "img_path": [
            "062.jpg",
            "063.jpg"
        ]
    },
    {
        "start_time": 350,
        "end_time": 360,
        "text": "lên qua cầu rịch miểu trong tất cả các ngày trong tuần ở cả hai hướng Bến Tre và Tiền Giang hướng từ Tiền Giang đi bến tr sẽ cắm trong hai khung giờ từ 9 đến 11 gi và từ 15 đến 19 gi cùng ngày còn",
        "img_path": [
            "064.jpg",
            "065.jpg",
            "066.jpg"
        ]
    },
    {
        "start_time": 360,
        "end_time": 370,
        "text": "hướng ngược lại tức từ Bến Tre đi Tiền Giang sẽ cắm trong một khung giờ từ 15 đến 19 giờ hàng ngày trong 15 ngày thí",
        "img_path": [
            "067.jpg",
            "068.jpg",
            "069.jpg",
            "070.jpg",
            "071.jpg"
        ]
    },
    {
        "start_time": 370,
        "end_time": 380,
        "text": "điệm các ngành chức năng sẽ ghi nhận những ý kiến của người dân và doanh nghiệp vận tải về những bất cập và sẽ điều chỉnh cho hợp lý với tình hình thực tế thời gian qua cầu Trạch miểu nói hai",
        "img_path": [
            "072.jpg",
            "073.jpg"
        ]
    },
    {
        "start_time": 380,
        "end_time": 390,
        "text": "tỉnh Tiền Giang và Bến Tre thường xuyên xảy ra tình trạng kẹt xe nguyên nhân một phần là do xe tải nặng qua cầu Trạch miểu chạy lên dốc với tốc độ chậm khiến",
        "img_path": [
            "074.jpg",
            "075.jpg",
            "076.jpg"
        ]
    },
    {
        "start_time": 390,
        "end_time": 400,
        "text": "dòng xe bị ùm ứ cầu Trạch miểu hiện có khoảng 20.000 xe qua cầu vượt gấp ba lần thiết kế cho phép của công trình cầu Rạch miểu hai cách cầu hiện hữu 3,8 km",
        "img_path": [
            "077.jpg",
            "078.jpg"
        ]
    },
    {
        "start_time": 400,
        "end_time": 410,
        "text": "được khởi công vào tháng 3 năm 2023 và dự kiến sẽ đưa vào sử dụng vào năm 2025 chiều qua trên quốc lộ 1A đoạn qua",
        "img_path": [
            "079.jpg"
        ]
    },
    {
        "start_time": 410,
        "end_time": 420,
        "text": "huyện Châu Thành tỉnh Tiền Giang Người dân phát hiện một nam thanh niên nằm cạnh xe máy sau tiếng cày Lê kéo dài dưới đường vụ Việt đã được trình báo cơ quan chức",
        "img_path": [
            "080.jpg",
            "081.jpg",
            "082.jpg"
        ]
    },
    {
        "start_time": 420,
        "end_time": 430,
        "text": "năng Theo thông tin ban đầu khoảng 13:20 trên địa bàn ấp Long Thạnh xã Long An huyện Châu Thành Người dân phát hiện một nam TH niên Hơn 20 tuổi đang nằm bất độn",
        "img_path": [
            "083.jpg"
        ]
    },
    {
        "start_time": 430,
        "end_time": 440,
        "text": "cạnh chiếc xe máy mang bị kiểm soát tỉnh Tiền Giang phía trước có chiếc xe tải mang bị kiểm soát tỉnh Cà dinin cũng đang dựng trên đường nam thanh niên bất tỉnh đợ người dân và tài xế xe tải sở",
        "img_path": [
            "084.jpg",
            "085.jpg"
        ]
    },
    {
        "start_time": 440,
        "end_time": 450,
        "text": "cứu và đưa đến bệnh viện Đại cấp cứu theo người dân nạn nhân có biểu hiện x xỉn tại hiện trường hai phương tiện nằm chiếm gần hết hai ln đường khiến giao thông ùng ứ dù việc đang được tiếp tục",
        "img_path": [
            "086.jpg",
            "087.jpg",
            "088.jpg"
        ]
    },
    {
        "start_time": 450,
        "end_time": 460,
        "text": "làm rõ công an hai tỉnh Vĩnh Long và Hậu Giang vừa phối hợp phá nhanh vụ án bắt cc đội tỷ đồng tiền chuộ nạn nhân bị bắt",
        "img_path": [
            "089.jpg",
            "090.jpg"
        ]
    },
    {
        "start_time": 460,
        "end_time": 470,
        "text": "vào ngày 10 tháng 5 tại huyện Châu Thành A tỉnh Hậu Giang và được giải cứu chưa đầy ha ngày sau đó tại huyện Long Hồ tỉnh Vĩnh Long nạn nhân là mvc sinh năm 1990 là",
        "img_path": [
            "091.jpg",
            "092.jpg"
        ]
    },
    {
        "start_time": 470,
        "end_time": 480,
        "text": "phó giám đốc Công ty tư vấn thiết kế thi công nội ngoại thất tại thành phố Cần Thơ đến rạng sáng ngày 12 tháng 5 sau",
        "img_path": [
            "093.jpg",
            "094.jpg"
        ]
    },
    {
        "start_time": 480,
        "end_time": 490,
        "text": "khi xác định nơi giữ nạn nhân là một căn nhà đang thuê trên đi bàn huyện Long Hồ tỉnh Vĩnh Long công an tỉnh Hậu Giang công an tỉnh Vĩnh Long bố trí lực lượng V Bắc trong quá trình tiếp cận của lực",
        "img_path": [
            "095.jpg"
        ]
    },
    {
        "start_time": 490,
        "end_time": 500,
        "text": "lượng chức năng đối tượng đã dùng dao uy hiếp đe dọa sát hại nạn nhân yêu cầu lực lượng công an cung cấp một ô tô để đối tượng tổ thoát Tuy nhiên các lực lượng đã phối hợp khống chế đối tượng và giải",
        "img_path": [
            "096.jpg",
            "097.jpg"
        ]
    },
    {
        "start_time": 500,
        "end_time": 510,
        "text": "cứu thành công nạn nhân thu giữ nhiều hung khí và tan vật có liên quan công an tỉnh Hậu Giang đã trao quyết định khen và thưởng nóng cho các lực lượng tham gia phá nhanh vụ",
        "img_path": [
            "098.jpg",
            "099.jpg"
        ]
    },
    {
        "start_time": 510,
        "end_time": 520,
        "text": "án chiều 14 tháng 5 sở y tế Đồng Nai cho biết hiện Chỉ còn bệnh nhi 7 tuổi ngũ huyện Cẩm Mỹ bị Ngô độc nặng sâu ăn bánh mị đang điều trị tại bệnh viện Nhi Đồng",
        "img_path": [
            "100.jpg",
            "101.jpg"
        ]
    },
    {
        "start_time": 520,
        "end_time": 530,
        "text": "Đồng Nai toàn bộ hơn 500 bệnh nhân khác đã xuất viện số gần hai tuần được điều trị tích cực bệnh nhân tdn đã cà được máy thở cử",
        "img_path": [
            "102.jpg",
            "103.jpg"
        ]
    },
    {
        "start_time": 530,
        "end_time": 540,
        "text": "động tay chân và đang trong giai đoạn điều trị phục hồi sau vụ ngộ độc quy mô lớn xảy ra viện y tế công cộng thành phố Hồ Chí Minh và các bệnh viện đã lấy 29",
        "img_path": [
            "104.jpg"
        ]
    },
    {
        "start_time": 540,
        "end_time": 550,
        "text": "mẫu bệnh phẩm đưa đi xét nghiệm bằng phương pháp PC và cy phân Tìm tác nhân gây ngộ độc kết quả có 16/29 mẫu dương tính đ với hai chuẩn vi khuẩn samonella",
        "img_path": [
            "105.jpg",
            "106.jpg"
        ]
    },
    {
        "start_time": 550,
        "end_time": 560,
        "text": "và Ecoli 9/29 mẫu dương tính với vi khuẩn Ecoli ngoài ra kết quả kiểm nghiệm mẫu thực phẩm lấy tại cơ sở bánh mì C bă ghi nhận 4/8 mẫu thực phẩm như pate thịt",
        "img_path": [
            "107.jpg",
            "108.jpg",
            "109.jpg"
        ]
    },
    {
        "start_time": 560,
        "end_time": 570,
        "text": "heo đả Qua chế biến chả lụa V mối chua có kết quả phát hiện vi khuẩn samonella còn tại tỉnh Vĩnh Phúc Bệnh",
        "img_path": [
            "110.jpg"
        ]
    },
    {
        "start_time": 570,
        "end_time": 580,
        "text": "viện hữu nghị Lạc Việt vào chiều qua cho biết vừa tiếp nhận hơn 220 công nhân nhập viện với biểu hiện ngộ độc thực phẩm",
        "img_path": [
            "111.jpg"
        ]
    },
    {
        "start_time": 580,
        "end_time": 590,
        "text": "các công nhân nhập viện trong tình trạng Sốt đau bụng và nôn ói bệnh nhân cho biết các triệu chứng xuất hiện sau bữa ăn trưa ở công ty ngoài ra nhiều công nhân khác cũng đã được đưa đến cấp cứu",
        "img_path": [
            "112.jpg",
            "113.jpg",
            "114.jpg"
        ]
    },
    {
        "start_time": 590,
        "end_time": 600,
        "text": "tại bệnh viện đa khoa tỉnh Vĩnh Phúc Theo thông tin ban đầu các công nhân ngộ độc thuộc công ty trách nhiệm hữu hạn sinw eer Việt Nam khu công nghiệp khai",
        "img_path": [
            "115.jpg",
            "116.jpg",
            "117.jpg"
        ]
    },
    {
        "start_time": 600,
        "end_time": 610,
        "text": "quan thành phố Vĩnh Yên đây là công ty 100 vốn đầu tư của Hàn Quốc chuyên sản xuất các mặt hàng may mặt xuất khẩu ngay sau khi xả V Việ sở y tế Vĩnh Phúc Đã",
        "img_path": [
            "118.jpg"
        ]
    },
    {
        "start_time": 610,
        "end_time": 620,
        "text": "đến chỉ đạo công tác cấp cứu Bệnh nhân đồng thời yêu cầu các cơ quan chuyên môn tiến hành điều tra nguyên nhân vụ việc trong phần tiếp theo của chương",
        "img_path": [
            "119.jpg",
            "120.jpg"
        ]
    },
    {
        "start_time": 620,
        "end_time": 630,
        "text": "trình cảnh sát pháp Phát động một cuộc truy nã lớn sau vụ cướp xe chở tù nhân với mức giá 200 đô la m kg sản",
        "img_path": [
            "121.jpg"
        ]
    },
    {
        "start_time": 630,
        "end_time": 640,
        "text": "lượng tiêu campos năm nay giảm mạnh do hạng Hán [âm nhạc] một vụ cướp xe chở tù nhân đã xảy ra ở",
        "img_path": [
            "122.jpg",
            "123.jpg",
            "124.jpg"
        ]
    },
    {
        "start_time": 640,
        "end_time": 650,
        "text": "miền bắc nước Pháp hôm 14 tháng 5 hai cả ngục bị bắn chết ba người khác bị thương nặng một từ nhân trốn thoát Bộ trưởng Nội vụ Jan damin cho biết cảnh sát đã",
        "img_path": [
            "125.jpg"
        ]
    },
    {
        "start_time": 650,
        "end_time": 660,
        "text": "phát động một cuộc truy nã lớn theo nhà chức trách những kẻ mang vũ khí hạng nặng đã phục kích một chiếc xe tải của nhà tù để giải thoát một tù nhân",
        "img_path": [
            "126.jpg",
            "127.jpg"
        ]
    },
    {
        "start_time": 660,
        "end_time": 670,
        "text": "vụ tấn công được dàn dựng trước xảy ra vào khoảng 11 gi trưa theo giờ địa phương tại một trạm thu phí ở xã anvin tu vung not mandi hình ảnh trên mạng xã",
        "img_path": [
            "128.jpg"
        ]
    },
    {
        "start_time": 670,
        "end_time": 680,
        "text": "hội cho thấy ít nhất hai người đàn ông đội mũ trùm đầu mang súng trường đi vòng gần một chiếc SUV Đang móc cháy chiếc SUV có vẻ đã đâm vào đầu chiếc xe chở tù",
        "img_path": [
            "129.jpg",
            "130.jpg"
        ]
    },
    {
        "start_time": 680,
        "end_time": 690,
        "text": "nhân truyền thông địa phương đưa tin tên tù nhân bỏ trốn là mohammed amra 30 tuổi một nguồn tin cảnh sát pháp cho biết tên này bị nghi ngờ ra lệnh giết người ở mse",
        "img_path": [
            "131.jpg",
            "132.jpg"
        ]
    },
    {
        "start_time": 690,
        "end_time": 700,
        "text": "và là kẻ cầm đầu một đường dây buôn bán ma túy Theo nhận định của giới chuyên gia tình trạng thiếu Chip băng thông cao sẽ",
        "img_path": [
            "133.jpg"
        ]
    },
    {
        "start_time": 700,
        "end_time": 710,
        "text": "kéo dài đến hết năm nay thậm chí sang cả năm sau nguyên nhân của tình trạng eo hẹp nguồn cung này chủ yếu do sự bùng nổ của công nghệ Trí Tuệ Nhân Tạo",
        "img_path": [
            "134.jpg"
        ]
    },
    {
        "start_time": 710,
        "end_time": 720,
        "text": "ai với chuyên gia đánh giá quá trình chế tạo những loại chip này ngày càng phức tạp trong khi việc để mạnh sản xuất gặp không ít trở ngại theo một báo cáo chu kỳ sản xuất chiếc bộ nhớ ban thông cao",
        "img_path": [
            "135.jpg",
            "136.jpg",
            "137.jpg"
        ]
    },
    {
        "start_time": 720,
        "end_time": 730,
        "text": "lâu hơn Từ 1,5 đến 2 tháng sơ giới chu kỳ sản xuất chip bộ nhớ ddr5 sử dụng trong máy tính cá nhân và máy chủ trong khi đó các gã kh lộ công nghệ như",
        "img_path": [
            "138.jpg",
            "139.jpg"
        ]
    },
    {
        "start_time": 730,
        "end_time": 740,
        "text": "Microsoft Amazon hay Google đang để mạnh đầu tư cơ sở h tầng công nghệ dựa trên ai bao gồm các chiếc bộ nhớ hiệu suất cao để huấn luyện và đào tạo ai từ đó",
        "img_path": [
            "140.jpg",
            "141.jpg",
            "142.jpg",
            "143.jpg"
        ]
    },
    {
        "start_time": 740,
        "end_time": 750,
        "text": "thúc đẩy nhu cầu thị trường với loại chiếp này SK hx và Micon hai nhà cung cấp lớn nhất thế giới về chip bộ nhớ cho biết chip bộ nhớ hiệu suất cao gần như",
        "img_path": [
            "144.jpg",
            "145.jpg",
            "146.jpg"
        ]
    },
    {
        "start_time": 750,
        "end_time": 760,
        "text": "trong tình trạng cháy hàng để đáp ứng nhu cầu tăng mạnh đã có kế hoạch để mạnh sản xuất lên gấp đôi thậm chí gấp ba lần trong năm nay",
        "img_path": [
            "147.jpg",
            "148.jpg"
        ]
    },
    {
        "start_time": 760,
        "end_time": 770,
        "text": "trong những tuần gần đây ở một số vùng của Campuchia nhiệt độ lên tới 43 đ c thời tiết khắc nhiệt đã ảnh hưởng nghiêm trọng đến đồn điện tiêu ở miền Nam Đức này khiến nông dân xem như trắng tay",
        "img_path": [
            "149.jpg"
        ]
    },
    {
        "start_time": 770,
        "end_time": 780,
        "text": "trong năm nay Đồng Điền tiêu ch laem ở vùng Cambo gần như hoan tàn sau đợt hàng Hán kéo dài và nhiệt độ Khắc Nghiệt những hiện",
        "img_path": [
            "150.jpg",
            "151.jpg"
        ]
    },
    {
        "start_time": 780,
        "end_time": 790,
        "text": "tượng cực đoan này không chỉ ảnh hưởng đến vụ thu hoạch mà còn ảnh hưởng đến chất lượng của tiêu vốn phải đáp ứng những tiêu chuẩn rất khắc khe hạt tiêu campos được các đô bếp giỏi trên khắp",
        "img_path": [
            "152.jpg",
            "153.jpg"
        ]
    },
    {
        "start_time": 790,
        "end_time": 800,
        "text": "thế giới đánh giá cao nhờ hương vị cay nồng cùng hương hoa và tinh dầu bạc hà được bán trong các cửa hàng đồ ăn ngon với giá khoảng 200 EUR m kg Liên minh",
        "img_path": [
            "154.jpg"
        ]
    },
    {
        "start_time": 800,
        "end_time": 810,
        "text": "châu Âu đã công nhận hạt tiêu campo với nhãn chỉ dẫn địa lý được bảo vệ vào năm 2016 sản lượng vùng Đạt 120 tấn vào năm",
        "img_path": [
            "155.jpg",
            "156.jpg"
        ]
    },
    {
        "start_time": 810,
        "end_time": 820,
        "text": "ngoái tập trung ở một số đồng bằng nhỏ gần Vịnh Thái Lan theo canus chủ tịch hiệp hội xúc tiến hạt tiêu campo sẵn lượng sẽ D giả một nửa trong năm nay và",
        "img_path": [
            "157.jpg",
            "158.jpg"
        ]
    },
    {
        "start_time": 820,
        "end_time": 830,
        "text": "xuất khẩu có thể gặp tình trạng thiếu hục vào năm 2025 thưa quý vị ngày 13 tháng 5 vua tr Đệ Tam của nước Anh đã thực hiện nghi",
        "img_path": [
            "159.jpg"
        ]
    },
    {
        "start_time": 830,
        "end_time": 840,
        "text": "thức chuyển giao tước hiệu đại tá chỉ huy quân đoàn Không quân anh một tước hiệu luôn bên ông trong suốt 32 năm cho Hoàng Tử William phát biểu trong buổi lễ chuyển",
        "img_path": [
            "160.jpg",
            "161.jpg"
        ]
    },
    {
        "start_time": 840,
        "end_time": 850,
        "text": "giao tức hiệu ông khen ngợi Hoàng Tử William là một phi công rất giỏi nghi thức diễn ra ngay trước một chiếc trực thăng Apache cũng như trước sự chứng kiến của đội phục vụ tại Bảo tàn không",
        "img_path": [
            "162.jpg",
            "163.jpg",
            "164.jpg"
        ]
    },
    {
        "start_time": 850,
        "end_time": 860,
        "text": "quân ở miền Nam nước Anh sự kiện là lần xuất hiện mới nhất của vua char đại Tam gần 3 tháng sau khi cung điện Buckingham thông báo Ông đang",
        "img_path": [
            "165.jpg"
        ]
    },
    {
        "start_time": 860,
        "end_time": 870,
        "text": "điều trị ung thư hoàng tử William 41 tuổi cũng đã tạm dừng công việc chính thức trong vài tuần hồi tháng 3 và tháng 4 để chăm sóc vợ sau khi cô thông báo",
        "img_path": [
            "166.jpg",
            "167.jpg"
        ]
    },
    {
        "start_time": 870,
        "end_time": 880,
        "text": "hóa trị phòng ngừa ung thư việc chuyển giao tước vị được công bố vào tháng 8 năm ngoái Sau khi vua char lên ngồi ngay sau lễ chuyển giao",
        "img_path": [
            "168.jpg",
            "169.jpg",
            "170.jpg"
        ]
    },
    {
        "start_time": 880,
        "end_time": 890,
        "text": "tước vị hoàng tử William đã ngay lập tức thực hiện công việc ở vị trí mới xem quá trình huấn luyện và nhận thông tin tóm tắt về công việc hiện tại của quân đoàn Không",
        "img_path": [
            "171.jpg",
            "172.jpg",
            "173.jpg"
        ]
    },
    {
        "start_time": 890,
        "end_time": 900,
        "text": "quân một bảo tàng ở các tiểu vương quốc Ả Rập Thống nhất uae mong muốn đem lại",
        "img_path": [
            "174.jpg",
            "175.jpg"
        ]
    },
    {
        "start_time": 900,
        "end_time": 910,
        "text": "trải nghiệm nhệ thuật có 102 cho khách tham quan khi kết hợp hình ảnh Âm Thanh Và thậm chí cả mùi hương nằm giữa trung tâm mua sóng Dubai",
        "img_path": [
            "176.jpg"
        ]
    },
    {
        "start_time": 910,
        "end_time": 920,
        "text": "cuae là bảo tàng at gồm 14 phòng Trư bày khác nhau ban quản lý bảo tàng gọi nơi này là kết quả của cuộc hôn phối giữa nghệ thuật và công nghệ đem lại trải",
        "img_path": [
            "177.jpg"
        ]
    },
    {
        "start_time": 920,
        "end_time": 930,
        "text": "nghiệm choáng ngợp cho du khách ngay khi Họ vừa bước chân qua cửa ngay từ cổng vào bạn sẽ thấy một con sóng khổng lồ tuyệt đẹp mỗi phòng Trương bày có một mùi hương riêng bạn sẽ cảm nhận những",
        "img_path": [
            "178.jpg",
            "179.jpg",
            "180.jpg"
        ]
    },
    {
        "start_time": 930,
        "end_time": 940,
        "text": "hình ảnh bạn nhìn thấy bạn cảm nhận thông qua âm thanh và mùi hương bảo tàng cũng mời du khách tham gia vào việc tạo không khí nghệ thuật từ vẽ tranh để",
        "img_path": [
            "181.jpg",
            "182.jpg",
            "183.jpg"
        ]
    },
    {
        "start_time": 940,
        "end_time": 950,
        "text": "chiếu lên màn hình cho đến chơi piano để những khách tham quan khác cùng thưởng thức bảo tàng at khai trương từ tháng 2 năm nay do công ty thiết kế kỹ Thục số Hàn Quốc district sản xuất triển lãm",
        "img_path": [
            "184.jpg"
        ]
    },
    {
        "start_time": 950,
        "end_time": 960,
        "text": "khai trương của Bảo tàn mang tên thiên nhiên vĩnh cửu nhà mục đích nhắc nhở mọi người về tầng quan trọng của thiên nhiên và bảo vệ môi trường ngày 14 tháng 5 liên hoan phim",
        "img_path": [
            "185.jpg",
            "186.jpg",
            "187.jpg",
            "188.jpg",
            "189.jpg"
        ]
    },
    {
        "start_time": 960,
        "end_time": 970,
        "text": "can lần thứ 77 đã khai mạc tại pháp sự kiện sẽ kéo dài đến ngày 25 tháng 5 tham gia tranh giải Cành Cọ Vàng năm nay",
        "img_path": [
            "190.jpg",
            "191.jpg",
            "192.jpg"
        ]
    },
    {
        "start_time": 970,
        "end_time": 980,
        "text": "là 22 tác phẩm của các nhà làm phim đến từ nhiều quốc gia trong đó có những tên tuổi lớn như Francis for coola David",
        "img_path": [
            "193.jpg",
            "194.jpg"
        ]
    },
    {
        "start_time": 980,
        "end_time": 990,
        "text": "cronberg jogos latim ban giám khảo gồm chính thành viên Do đạo diễn người Mỹ grita gwi làm chủ tịch sẽ chọn ra bộ phim xuất sắc nhất để",
        "img_path": [
            "195.jpg",
            "196.jpg"
        ]
    },
    {
        "start_time": 990,
        "end_time": 1000,
        "text": "trao giải Cành Cọ Vàng vào ngày 25 tháng 5 Mỗ màn sự kiện năm nay là bộ phim hồi thứ hai khủ đạo diễn nước chủ nhà conta dupia sự kiện năm nay có thêm",
        "img_path": [
            "197.jpg",
            "198.jpg"
        ]
    },
    {
        "start_time": 1000,
        "end_time": 1010,
        "text": "hạng một tranh giải cho Tám tác phẩm nhập vai thực tế ảo là một phần của dự án can on air nhằm phát triển ngành công",
        "img_path": [
            "199.jpg",
            "200.jpg"
        ]
    },
    {
        "start_time": 1010,
        "end_time": 1020,
        "text": "nghiệp văn hóa sáng tạo tại địa phương những thông tin vừa rồi cũng đã kết thúc chương trình 60 Giây sáng n của chúng tôi Hẹn gặp lại quý vị trong chương trình 60 Giây chiều nay còn bây",
        "img_path": [
            "201.jpg"
        ]
    },
    {
        "start_time": 1020,
        "end_time": 1030,
        "text": "giờ Xin kính chào tạm biệt [Vỗ tay] [âm nhạc]",
        "img_path": [
            "202.jpg",
            "203.jpg"
        ]
    }
]